pyservice/__init__.py
pyservice/action.py
pyservice/context.py
pyservice/organizer.py
pyservice-0.0.11.dist-info/LICENSE
pyservice-0.0.11.dist-info/WHEEL
pyservice-0.0.11.dist-info/METADATA
pyservice-0.0.11.dist-info/RECORD
