Metadata-Version: 2.1
Name: pyservice
Version: 0.0.11
Summary: A light-service like project in Python
Home-page: https://github.com/adomokos/pyservice
Keywords: workflow,functional,pyservice
Author: Attila Domokos
Author-email: adomokos@gmail.com
Requires-Python: >=3.6,<4.0
Classifier: Programming Language :: Python :: 3
Classifier: Programming Language :: Python :: 3.6
Classifier: Programming Language :: Python :: 3.7
Classifier: Programming Language :: Python :: 3.8
Project-URL: Documentation, https://github.com/adomokos/pyservice
Project-URL: Repository, https://github.com/adomokos/pyservice
